sensirion_shdlc_sfa3x/__init__.py
sensirion_shdlc_sfa3x/device.py
sensirion_shdlc_sfa3x/device_errors.py
sensirion_shdlc_sfa3x/example.py
sensirion_shdlc_sfa3x/response_types.py
sensirion_shdlc_sfa3x/version.py
sensirion_shdlc_sfa3x/commands/__init__.py
sensirion_shdlc_sfa3x/commands/device_information.py
sensirion_shdlc_sfa3x/commands/device_reset.py
sensirion_shdlc_sfa3x/commands/read_measured_values.py
sensirion_shdlc_sfa3x/commands/start_measurement.py
sensirion_shdlc_sfa3x/commands/stop_measurement.py
sensirion_shdlc_sfa3x-0.1.0.dist-info/LICENSE
sensirion_shdlc_sfa3x-0.1.0.dist-info/METADATA
sensirion_shdlc_sfa3x-0.1.0.dist-info/WHEEL
sensirion_shdlc_sfa3x-0.1.0.dist-info/top_level.txt
sensirion_shdlc_sfa3x-0.1.0.dist-info/RECORD
